{
    "fluentMethods": true,
    "relationships": [],
    "fields": [
        {
            "fieldName": "nome",
            "fieldType": "String",
            "fieldValidateRules": [
                "required"
            ]
        },
        {
            "fieldName": "tipo",
            "fieldType": "TipoServico",
            "fieldValues": "PAQ,ASS,PRS",
            "fieldValidateRules": [
                "required"
            ]
        }
    ],
    "changelogDate": "20190217161758",
    "entityTableName": "descricao_servico",
    "dto": "no",
    "pagination": "no",
    "service": "serviceClass",
    "jpaMetamodelFiltering": true
}